Metadata-Version: 2.1
Name: factordb-python
Version: 1.3.0
Summary: The FactorDB client library with Python
Home-page: https://github.com/ryosan-470/factordb-python
Author: Ryosuke SATO (@ryosan-470)
Author-email: rskjtwp@gmail.com
License: MIT License
Platform: UNKNOWN
Classifier: Development Status :: 4 - Beta
Classifier: Environment :: Console
Classifier: Programming Language :: Python :: 2
Classifier: Programming Language :: Python :: 2.7
Classifier: Programming Language :: Python :: 3
Classifier: Programming Language :: Python :: 3.4
Classifier: Programming Language :: Python :: 3.5
Classifier: Programming Language :: Python :: 3.6
Classifier: Programming Language :: Python :: 3.7
Classifier: Programming Language :: Python :: 3.8
Classifier: Topic :: Utilities
